drfgen/__init__.py
drfgen/cli.py
drfgen/main.py
drfgen/core/__init__.py
drfgen/core/venv.py
drfgen/generator/__init__.py
drfgen/generator/project_builder.py
drfgen/prompts/__init__.py
drfgen/prompts/api_versioning.py
drfgen/prompts/auth_method.py
drfgen/prompts/database.py
drfgen/prompts/django_version.py
drfgen/prompts/dockerize.py
drfgen/prompts/drf_version.py
drfgen/prompts/settings_structure.py
drfgen/prompts/swagger.py
drfgen/steps/__init__.py
drfgen/steps/custom_drfgen_startapp.py
drfgen/steps/install_common_packages.py
drfgen/steps/install_drf.py
drfgen/steps/save_config.py
drfgen/steps/swagger.py
drfgen/utils/__init__.py
drfgen/utils/pypi.py
drfgen-0.1.3.dist-info/METADATA
drfgen-0.1.3.dist-info/WHEEL
drfgen-0.1.3.dist-info/entry_points.txt
drfgen-0.1.3.dist-info/top_level.txt
drfgen-0.1.3.dist-info/RECORD
