Metadata-Version: 2.4
Name: drfgen
Version: 0.1.3
Summary: A CLI tool to bootstrap Django REST Framework projects quickly and easily.
Home-page: https://github.com/tahericode/DRFgen.git
Author: Mohammadreza Taheri
Author-email: mrtcode2@gmail.com
Classifier: Programming Language :: Python :: 3
Classifier: Framework :: Django
Classifier: Operating System :: OS Independent
Classifier: License :: OSI Approved :: MIT License
Classifier: Topic :: Software Development :: Code Generators
Requires-Python: >=3.8
Requires-Dist: click>=8.0
Requires-Dist: questionary>=2.0
Requires-Dist: requests>=2.0
Dynamic: author
Dynamic: author-email
Dynamic: classifier
Dynamic: description
Dynamic: description-content-type
Dynamic: home-page
Dynamic: requires-dist
Dynamic: requires-python
Dynamic: summary
